timberlake/__init__.py
timberlake/aws.py
timberlake/cli.py
timberlake/common.py
timberlake/config.py
timberlake/log.py
timberlake/mitre.py
timberlake/sequence.py
timberlake/settings.py
timberlake/testcase.py
timberlake/types.py
timberlake/vectr.py
timberlake-1.0.4.dist-info/LICENSE
timberlake-1.0.4.dist-info/METADATA
timberlake-1.0.4.dist-info/WHEEL
timberlake-1.0.4.dist-info/entry_points.txt
timberlake-1.0.4.dist-info/RECORD
