Metadata-Version: 2.1
Name: timberlake
Version: 1.0.4
Summary: AWS attack automation utility
License: MIT
Author: 2XXE
Author-email: root@example.com
Requires-Python: >=3.8,<4.0
Classifier: License :: OSI Approved :: MIT License
Classifier: Programming Language :: Python :: 3
Classifier: Programming Language :: Python :: 3.8
Classifier: Programming Language :: Python :: 3.9
Classifier: Programming Language :: Python :: 3.10
Classifier: Programming Language :: Python :: 3.11
Classifier: Programming Language :: Python :: 3.12
Classifier: Programming Language :: Python :: 3.13
Requires-Dist: Jinja2 (>=3.0.1,<4.0.0)
Requires-Dist: boto3 (>=1.17.111,<2.0.0)
Requires-Dist: desert (>=2020.11.18,<2021.0.0)
Requires-Dist: gql[all] (>=3.4.0,<4.0.0)
Requires-Dist: marshmallow (==3.18.0)
Requires-Dist: marshmallow-enum (>=1.5.1,<2.0.0)
Requires-Dist: pydantic (>=1.10.2,<2.0.0)
Requires-Dist: pyyaml (>=6.0.2,<7.0.0)
